{"accesspro":"PROS login","actualite":"News","actualiteaero":"Aviation news","aerocontact":"Aerocontact","aerodesc1":"<b>AEROCONTACT<\/b>, your Aviation and Aerospace network : news, jobs, internships, Register CV, directory, training, videos, ...","aerodesc2":"The first aviation and aerospace portal.","aeronautique":"aeronautical","aeroslogan":"Aerocontact, your Aerospace Professional Network","annuaire":"Directory","candidat":"Candidate","compte":"Account","conseil":"#NO#","conseils":"Career advice","cvg":"Terms and conditions","cvpremium":"CV Premium","depotcv":"Register CV","ellesexposent":"Exhibitors","ellesrecrutent":"They hire","emploi":"Job","emploienergie":"#NO#","emploiinge":"#NO#","emploitech":"#NO#","ensavoirplus":"Learn more","envoirplus":"see more","espacepro":"Our services","et":"and","formation":"Training","groupeaero":"Aerocontact Group","logout":"Logout","meconnecter":"Login","mesalertes":"My alerts","mescandidatures":"My applications","mesinfos":"My info","meslettres":"My cover letters","metier":"#NO#","moncompte":"My account","monprofil":"My profile","nosservices":"Our services","nouscontacter":"Contact us","nouveau":"new","precedent":"Back","produitheque":"Products","profil":"Profile","quisommesnous":"About us","rechercher":"Search","recruteur":"PROS","reduire":"less","reseauxsociaux":"Social Networks","retrouvez":"","rubriques":"Sections","salonvirtuel":"Virtual aviation exhibition","stage":"Internship","suivant":"Next","textcookies":"By continuing you are agreeing to our use of cookies","versionen":"English version","versionfr":"French version","video":"Videos"}